link/__init__.py
link/kvstore/__init__.py
link/kvstore/core.py
link/kvstore/driver.py
link/kvstore/test/__init__.py
link/kvstore/test/core.py
link/kvstore/test/driver.py
link.kvstore-1.0.dist-info/DESCRIPTION.rst
link.kvstore-1.0.dist-info/METADATA
link.kvstore-1.0.dist-info/RECORD
link.kvstore-1.0.dist-info/WHEEL
link.kvstore-1.0.dist-info/metadata.json
link.kvstore-1.0.dist-info/top_level.txt
