Metadata-Version: 2.0
Name: link.kvstore
Version: 1.0
Summary: Database agnostic key/value store API
Home-page: https://github.com/linkdd/link.kvstore
Author: David Delassus
Author-email: david.jose.delassus@gmail.com
License: MIT
Keywords: link key value store
Platform: UNKNOWN
Classifier: Development Status :: 5 - Production/Stable
Classifier: License :: OSI Approved :: MIT License
Classifier: Operating System :: OS Independent
Classifier: Topic :: Utilities
Classifier: Topic :: Software Development :: Libraries :: Python Modules
Classifier: Intended Audience :: Developers
Classifier: Programming Language :: Python
Classifier: Programming Language :: Python :: 2.7
Classifier: Programming Language :: Python :: 3
Classifier: Programming Language :: Python :: 3.4
Classifier: Programming Language :: Python :: 3.5
Classifier: Programming Language :: Python :: Implementation :: CPython
Requires-Dist: b3j0f.utils (>=1.4.3)
Requires-Dist: link.middleware (>=1.5)
Requires-Dist: mock (>=2.0.0)
Requires-Dist: six (>=1.10.0)
